{
  "neoforge:conditions": [
    {
      "type": "neoforge:not",
      "value": {
        "type": "neoforge:tag_empty",
        "tag": "c:ores/sapphire"
      }
    }
  ],
  "type": "resourcefish:fish_infusing",
  "chance": 1.0,
  "created_fish": "resourcefish:sapphire",
  "duration": 100,
  "fish": "resourcefish:emerald",
  "inputs": [
    {
      "count": 64,
      "tag": "c:gems/sapphire"
    },
    {
      "count": 64,
      "item": "minecraft:stone"
    },
    {
      "count": 64,
      "tag": "c:gems/sapphire"
    }
  ]
}